pyrxiv/__init__.py
pyrxiv/_version.py
pyrxiv/datamodel.py
pyrxiv/download.py
pyrxiv/extract.py
pyrxiv/fetch.py
pyrxiv/logger.py
pyrxiv/cli/__init__.py
pyrxiv/cli/cli.py
pyrxiv-1.0.1.dist-info/licenses/LICENSE
tests/__init__.py
tests/conftest.py
tests/test_datamodel.py
tests/test_download.py
tests/test_extract.py
tests/test_fetch.py
tests/test_logger.py
tests/data/2502.12144v1.pdf
tests/data/fetched_arxiv_ids.txt
tests/data/no_pdf_paper.txt
tests/data/sample.pdf
pyrxiv-1.0.1.dist-info/METADATA
pyrxiv-1.0.1.dist-info/WHEEL
pyrxiv-1.0.1.dist-info/entry_points.txt
pyrxiv-1.0.1.dist-info/top_level.txt
pyrxiv-1.0.1.dist-info/RECORD
