Metadata-Version: 2.4
Name: pyrxiv
Version: 1.0.1
Summary: A Python package for retrieving arXiv papers and filter them out with respect to some specific regex pattern.
Author-email: "Jose M. Pizarro" <jose.pizarro-blanco@bam.de>
Maintainer-email: "Jose M. Pizarro" <jose.pizarro-blanco@bam.de>
License: MIT License
Project-URL: Homepage, https://github.com/JosePizarro3/pyrxiv
Project-URL: Bug Tracker, https://github.com/JosePizarro3/pyrxiv/issues
Classifier: Natural Language :: English
Classifier: Intended Audience :: Science/Research
Classifier: Operating System :: OS Independent
Classifier: Programming Language :: Python
Classifier: Programming Language :: Python :: 3.10
Classifier: Programming Language :: Python :: 3.11
Classifier: Programming Language :: Python :: 3.12
Requires-Python: >=3.10
License-File: LICENSE
Requires-Dist: click>=8.2.1
Requires-Dist: pydantic~=2.10.5
Requires-Dist: structlog~=24.4.0
Requires-Dist: requests~=2.32.4
Requires-Dist: xmltodict~=0.14.2
Requires-Dist: pypdf~=5.7.0
Requires-Dist: pdfminer.six
Requires-Dist: langchain-community~=0.3.27
Requires-Dist: h5py
Provides-Extra: dev
Requires-Dist: mypy==1.0.1; extra == "dev"
Requires-Dist: ruff>=0.11.4; extra == "dev"
Requires-Dist: pytest; extra == "dev"
Requires-Dist: pytest-timeout; extra == "dev"
Requires-Dist: pytest-cov; extra == "dev"
Dynamic: license-file
